{"670873058": {"name": "ׂוסע", "bot_message_id": 6663, "index_question": 25, "current_question": 0, "index_q_work": 1, "value_q_work": 0, "index_q_level": 0, "value_q_level": 0, "count_send_resume": 1, "data_send_resume": "", "data_send_request": "18:25:06.330621", "answers": {"full_name": "ָגאם", "old": 123, "education": "גסרטו", "name_organization1": "גאגא", "year_ending": "גא", "speciality": "גא", "study_now": "גא", "location": "גא", "renting_house": "הא", "phone_number": "פגפג", "family_status": "סגמבמהום", "children": "גפאג", "military_service": "הא", "experience": "גאא", "shift_work": "הא", "business_trips": "הא", "housing_problem": "הא", "skill_PK": "הא", "knowledge_programms": "גא", "language_level": "(ְ1) – םאקאכםי", "contraindications": "גאג", "found_us": "גאג", "personal_qualities": "גאג", "work_experience": [{"period_employment": "00,33 033", "name_organization": "", "position_held": "", "reason_leaving": ""}], "level_of_claims": [{"work_period": "", "minimum_salary": "", "desired_salary": ""}]}}}